{
  "streamId": 1103,
  "date": "2015-08-30 11:54",
  "game": {
    "name": "Arma 3",
    "slug": "Arma-3"
  },
  "subcategory": {
    "name": "Zeus Games",
    "slug": "Zeus-Games",
    "onlyCategory": false,
    "playlist": [
      {
        "streamId": 1103,
        "date": "2015-08-30 11:54"
      },
      {
        "streamId": 1104,
        "date": "2016-01-30 22:11"
      },
      {
        "streamId": 1105,
        "date": "2016-04-20 13:00"
      }
    ]
  },
  "number": 1,
  "vimeoEmbedHtml": "<iframe src=\"https://player.vimeo.com/video/459799365?title=0&amp;byline=0&amp;portrait=0&amp;badge=0&amp;autopause=0&amp;player_id=0&amp;app_id=187937\" width=\"400\" height=\"300\" frameborder=\"0\" allow=\"autoplay; fullscreen\" allowfullscreen title=\"2015-08-30 11-54-00\"></iframe>",
  "bunnyId": "e452657b-3ffb-4c3a-a280-327f682661bb",
  "useBunny": true
}