{
  "streamId": 1469,
  "date": "2020-11-03 21:01",
  "game": {
    "name": "Subnautica",
    "slug": "Subnautica"
  },
  "subcategory": {
    "name": "Misc",
    "slug": "Misc",
    "onlyCategory": true,
    "playlist": [
      {
        "streamId": 1459,
        "date": "2020-10-28 11:20"
      },
      {
        "streamId": 1460,
        "date": "2020-10-28 20:28"
      },
      {
        "streamId": 1458,
        "date": "2020-10-29 11:18"
      },
      {
        "streamId": 1461,
        "date": "2020-10-30 11:14"
      },
      {
        "streamId": 1464,
        "date": "2020-10-31 16:25"
      },
      {
        "streamId": 1462,
        "date": "2020-10-31 22:51"
      },
      {
        "streamId": 1465,
        "date": "2020-11-01 15:32"
      },
      {
        "streamId": 1463,
        "date": "2020-11-02 11:07"
      },
      {
        "streamId": 1470,
        "date": "2020-11-02 11:07"
      },
      {
        "streamId": 1487,
        "date": "2020-11-02 11:07"
      },
      {
        "streamId": 1486,
        "date": "2020-11-03 11:28"
      },
      {
        "streamId": 1468,
        "date": "2020-11-03 20:09"
      },
      {
        "streamId": 1469,
        "date": "2020-11-03 21:01"
      },
      {
        "streamId": 1471,
        "date": "2020-11-04 11:02"
      },
      {
        "streamId": 1473,
        "date": "2020-11-06 11:08"
      },
      {
        "streamId": 1489,
        "date": "2020-11-07 12:05"
      },
      {
        "streamId": 1488,
        "date": "2020-11-07 21:45"
      }
    ]
  },
  "number": 13,
  "vimeoEmbedHtml": "<iframe src=\"https://player.vimeo.com/video/476129477?title=0&amp;byline=0&amp;portrait=0&amp;badge=0&amp;autopause=0&amp;player_id=0&amp;app_id=187937\" width=\"400\" height=\"300\" frameborder=\"0\" allow=\"autoplay; fullscreen\" allowfullscreen title=\"2020-11-03 21-01-41\"></iframe>",
  "bunnyId": "4d1c7b81-deaf-42e9-ba81-1493b7719228",
  "useBunny": true
}