{
  "streamId": 15078,
  "date": "2023-10-11 11:18",
  "game": {
    "name": "Valheim",
    "slug": "Valheim"
  },
  "subcategory": {
    "name": "Bacon Bay",
    "slug": "Bacon-Bay",
    "onlyCategory": false,
    "playlist": [
      {
        "streamId": 15075,
        "date": "2023-10-09 11:05"
      },
      {
        "streamId": 15076,
        "date": "2023-10-10 11:14"
      },
      {
        "streamId": 15077,
        "date": "2023-10-10 20:09"
      },
      {
        "streamId": 15078,
        "date": "2023-10-11 11:18"
      },
      {
        "streamId": 15079,
        "date": "2023-10-12 11:08"
      }
    ]
  },
  "number": 4,
  "bunnyId": "d9d0810a-462c-4e70-9351-c1b345bc0b35",
  "useBunny": true
}