{
  "streamId": 3724,
  "date": "2021-02-22 11:25",
  "game": {
    "name": "The Isle",
    "slug": "The-Isle"
  },
  "subcategory": {
    "name": "Misc",
    "slug": "Misc",
    "onlyCategory": true,
    "playlist": [
      {
        "streamId": 14179,
        "date": "2020-04-17 11:08"
      },
      {
        "streamId": 14182,
        "date": "2020-04-17 11:29"
      },
      {
        "streamId": 14190,
        "date": "2020-04-18 13:51"
      },
      {
        "streamId": 14193,
        "date": "2020-04-19 13:51"
      },
      {
        "streamId": 14189,
        "date": "2020-04-20 11:07"
      },
      {
        "streamId": 14187,
        "date": "2020-04-21 10:49"
      },
      {
        "streamId": 14186,
        "date": "2020-04-22 20:15"
      },
      {
        "streamId": 14180,
        "date": "2020-04-27 20:06"
      },
      {
        "streamId": 14184,
        "date": "2020-04-28 11:15"
      },
      {
        "streamId": 14181,
        "date": "2020-04-29 20:30"
      },
      {
        "streamId": 14191,
        "date": "2020-06-16 20:22"
      },
      {
        "streamId": 1417,
        "date": "2020-10-19 20:24"
      },
      {
        "streamId": 14188,
        "date": "2020-10-19 20:24"
      },
      {
        "streamId": 3712,
        "date": "2021-02-16 20:08"
      },
      {
        "streamId": 3743,
        "date": "2021-02-17 19:45"
      },
      {
        "streamId": 14183,
        "date": "2021-02-18 11:03"
      },
      {
        "streamId": 3722,
        "date": "2021-02-19 11:44"
      },
      {
        "streamId": 3734,
        "date": "2021-02-19 20:10"
      },
      {
        "streamId": 14192,
        "date": "2021-02-19 20:10"
      },
      {
        "streamId": 3723,
        "date": "2021-02-21 17:40"
      },
      {
        "streamId": 3724,
        "date": "2021-02-22 11:25"
      },
      {
        "streamId": 3725,
        "date": "2021-02-22 20:34"
      },
      {
        "streamId": 3726,
        "date": "2021-02-23 20:37"
      },
      {
        "streamId": 14185,
        "date": "2021-02-23 20:37"
      }
    ]
  },
  "number": 21,
  "bunnyId": "398a1d59-4a33-4932-9046-dd4bc0032bc1",
  "useBunny": true
}