{
  "streamId": 6888,
  "date": "2021-09-29 11:14",
  "game": {
    "name": "Hardspace: Shipbreaker",
    "slug": "Hardspace-Shipbreaker"
  },
  "subcategory": {
    "name": "Misc",
    "slug": "Misc",
    "onlyCategory": true,
    "playlist": [
      {
        "streamId": 6886,
        "date": "2021-09-28 11:10"
      },
      {
        "streamId": 6890,
        "date": "2021-09-28 20:21"
      },
      {
        "streamId": 6888,
        "date": "2021-09-29 11:14"
      },
      {
        "streamId": 6889,
        "date": "2021-09-29 20:27"
      },
      {
        "streamId": 6885,
        "date": "2021-09-30 11:17"
      },
      {
        "streamId": 6887,
        "date": "2021-10-01 20:17"
      }
    ]
  },
  "number": 3,
  "vimeoEmbedHtml": null,
  "bunnyId": "bbedbab7-7de1-45cf-be4e-dbacc134f291",
  "useBunny": true
}